jaxonnxruntime/__init__.py
jaxonnxruntime/backend.py
jaxonnxruntime/call_onnx.py
jaxonnxruntime/config_class.py
jaxonnxruntime/runner.py
jaxonnxruntime/version.py
jaxonnxruntime/core/__init__.py
jaxonnxruntime/core/handler.py
jaxonnxruntime/core/onnx_graph.py
jaxonnxruntime/core/onnx_node.py
jaxonnxruntime/core/onnx_utils.py
jaxonnxruntime/experimental/call_torch/Notes.md
jaxonnxruntime/experimental/call_torch/__init__.py
jaxonnxruntime/experimental/call_torch/call_torch.py
jaxonnxruntime/experimental/call_torch/call_torch_test_util.py
jaxonnxruntime/experimental/call_torch/tests/call_torch_test.py
jaxonnxruntime/experimental/call_torch/tests/d2l_torch.py
jaxonnxruntime/experimental/custom_ops/__init__.py
jaxonnxruntime/experimental/custom_ops/zeros_like.py
jaxonnxruntime/experimental/custom_ops/zeros_like_test.py
jaxonnxruntime/onnx_ops/__init__.py
jaxonnxruntime/onnx_ops/abs.py
jaxonnxruntime/onnx_ops/acos.py
jaxonnxruntime/onnx_ops/acosh.py
jaxonnxruntime/onnx_ops/add.py
jaxonnxruntime/onnx_ops/and_op.py
jaxonnxruntime/onnx_ops/argmax.py
jaxonnxruntime/onnx_ops/argmin.py
jaxonnxruntime/onnx_ops/asin.py
jaxonnxruntime/onnx_ops/asinh.py
jaxonnxruntime/onnx_ops/atan.py
jaxonnxruntime/onnx_ops/atanh.py
jaxonnxruntime/onnx_ops/averagepool.py
jaxonnxruntime/onnx_ops/batchnormalization.py
jaxonnxruntime/onnx_ops/bitshift.py
jaxonnxruntime/onnx_ops/cast.py
jaxonnxruntime/onnx_ops/castlike.py
jaxonnxruntime/onnx_ops/ceil.py
jaxonnxruntime/onnx_ops/clip.py
jaxonnxruntime/onnx_ops/concat.py
jaxonnxruntime/onnx_ops/constant.py
jaxonnxruntime/onnx_ops/constantofshape.py
jaxonnxruntime/onnx_ops/conv.py
jaxonnxruntime/onnx_ops/cos.py
jaxonnxruntime/onnx_ops/cosh.py
jaxonnxruntime/onnx_ops/div.py
jaxonnxruntime/onnx_ops/dropout.py
jaxonnxruntime/onnx_ops/einsum.py
jaxonnxruntime/onnx_ops/equal.py
jaxonnxruntime/onnx_ops/erf.py
jaxonnxruntime/onnx_ops/exp.py
jaxonnxruntime/onnx_ops/expand.py
jaxonnxruntime/onnx_ops/flatten.py
jaxonnxruntime/onnx_ops/gather.py
jaxonnxruntime-0.3.0.dist-info/LICENSE
jaxonnxruntime-0.3.0.dist-info/METADATA
jaxonnxruntime-0.3.0.dist-info/WHEEL
jaxonnxruntime-0.3.0.dist-info/top_level.txt
jaxonnxruntime-0.3.0.dist-info/RECORD
