Metadata-Version: 2.1
Name: jaxonnxruntime
Version: 0.3.0
Summary: Jaxonnxruntime: JAX based ONNX Runtime.
Author-email: Jaxonnxruntime team <jaxonnxruntime-dev@google.com>
Project-URL: homepage, https://github.com/google/jaxonnxruntime
Classifier: Development Status :: 3 - Alpha
Classifier: Intended Audience :: Developers
Classifier: Intended Audience :: Science/Research
Classifier: License :: OSI Approved :: Apache Software License
Classifier: Programming Language :: Python :: 3.7
Classifier: Topic :: Scientific/Engineering :: Artificial Intelligence
License-File: LICENSE
Requires-Dist: numpy
Requires-Dist: jax
Requires-Dist: jaxlib
Provides-Extra: all
Requires-Dist: onnx ==1.12.0 ; extra == 'all'
Provides-Extra: testing
Requires-Dist: mypy ; extra == 'testing'
Requires-Dist: pytest ; extra == 'testing'
Requires-Dist: pytest-cov ; extra == 'testing'
Requires-Dist: pytest-custom-exit-code ; extra == 'testing'
Requires-Dist: pytest-xdist ; extra == 'testing'
Requires-Dist: absl-py ; extra == 'testing'
